dataclass_array/__init__.py
dataclass_array/array_dataclass.py
dataclass_array/conftest.py
dataclass_array/field_utils.py
dataclass_array/ops.py
dataclass_array/shape_grammar.lark
dataclass_array/shape_parsing.py
dataclass_array/testing.py
dataclass_array/type_parsing.py
dataclass_array/typing.py
dataclass_array/vectorization.py
dataclass_array/utils/file_utils.py
dataclass_array/utils/inspect_utils.py
dataclass_array/utils/np_utils.py
dataclass_array/utils/py_utils.py
dataclass_array/utils/tree_utils.py
dataclass_array-1.5.2.dist-info/LICENSE
dataclass_array-1.5.2.dist-info/WHEEL
dataclass_array-1.5.2.dist-info/METADATA
dataclass_array-1.5.2.dist-info/RECORD
