Metadata-Version: 2.1
Name: dataclass_array
Version: 1.5.2
Summary: Dataclasses that behave like numpy arrays (with indexing, slicing, vectorization).
Keywords: dataclass,dataclasses,numpy,jax,tensorflow,array
Author-email: dataclass_array team <dataclass_array@google.com>
Requires-Python: >=3.11
Classifier: Programming Language :: Python :: 3
Classifier: Programming Language :: Python :: 3 :: Only
Classifier: License :: OSI Approved :: Apache Software License
Classifier: Intended Audience :: Science/Research
Classifier: Topic :: Software Development :: Libraries :: Python Modules
Requires-Dist: einops
Requires-Dist: etils[edc,enp,epath,epy,etree]
Requires-Dist: lark
Requires-Dist: numpy
Requires-Dist: typing_extensions
Requires-Dist: pytest ; extra == "dev"
Requires-Dist: pytest-xdist ; extra == "dev"
Requires-Dist: pylint>=2.6.0 ; extra == "dev"
Requires-Dist: pyink ; extra == "dev"
Requires-Dist: chex ; extra == "dev"
Requires-Dist: jax[cpu] ; extra == "dev"
Requires-Dist: tf-nightly ; extra == "dev"
Requires-Dist: torch ; extra == "dev"
Requires-Dist: sphinx-apitree[ext] ; extra == "docs"
Requires-Dist: dataclass_array[dev] ; extra == "docs"
Project-URL: changelog, https://github.com/google-research/dataclass_array/blob/main/CHANGELOG.md
Project-URL: documentation, https://dataclass-array.readthedocs.io
Project-URL: homepage, https://github.com/google-research/dataclass_array
Project-URL: repository, https://github.com/google-research/dataclass_array
Provides-Extra: dev
Provides-Extra: docs
